notifstats/__init__.py
notifstats/event_type.py
notifstats/main.py
notifstats/notification_type.py
notifstats-0.0.6.dist-info/LICENSE.txt
notifstats-0.0.6.dist-info/METADATA
notifstats-0.0.6.dist-info/WHEEL
notifstats-0.0.6.dist-info/top_level.txt
notifstats-0.0.6.dist-info/RECORD
