Metadata-Version: 2.1
Name: notifstats
Version: 0.0.6
Summary: Notification statistic collector
Home-page: https://github.com/kumparan/notification-stats
Author: I Putu Alfred Crosby
Author-email: alfred.crosby@kumparan.com
License: MIT
Download-URL: https://github.com/kumparan/notification-stats/archive/v_01.tar.gz
Keywords: Notification Statistic,Kumparan
Platform: UNKNOWN
Classifier: Development Status :: 4 - Beta
Classifier: Intended Audience :: Developers
Classifier: Topic :: Software Development :: Build Tools
Classifier: License :: OSI Approved :: MIT License
Classifier: Programming Language :: Python :: 3.5
Classifier: Programming Language :: Python :: 3.6
Requires-Python: >=3.6
Requires-Dist: google-cloud-bigquery (>=1.20.0)
